[{"queuename":"ATC-009_Activacion4G_XENA_Activacion4G","queuefolder":"B2B/ATC","useoutput":"False","usespecificcontent":"False","numberofcolumns":"2"},{"queuename":"ATC-009_Activacion4G_XENA_Activacion4G","queuefolder":"B2B/ATC","useoutput":"True","usespecificcontent":"False","numberofcolumns":"6"},{"queuename":"ATC-009_Activacion4G_XENA_Activacion4G","queuefolder":"B2B/ATC","useoutput":"False","usespecificcontent":"True","numberofcolumns":"7"},{"queuename":"ATC-009_Activacion4G_XENA_Activacion4G","queuefolder":"B2B/ATC","useoutput":"True","usespecificcontent":"True","numberofcolumns":"8"}]